<?xml version="1.0" encoding="utf-8" ?>
<Patch>
  <Operation Class="PatchOperationAddModExtension">
    <xpath>Defs/ThingDef[defName="Apparel_ShirtRuffle"]</xpath>
    <value>
      <li Class="LifeLessons.BillProficiencyExtension">
        <requirements>
          <li>Tailoring</li>
        </requirements>
      </li>
    </value>
    <success>Normal</success>
  </Operation>

  <Operation Class="PatchOperationAddModExtension">
    <xpath>Defs/ThingDef[defName="Apparel_Corset"]</xpath>
    <value>
      <li Class="LifeLessons.BillProficiencyExtension">
        <requirements>
          <li>Tailoring</li>
        </requirements>
      </li>
    </value>
    <success>Normal</success>
  </Operation>

  <Operation Class="PatchOperationAddModExtension">
    <xpath>Defs/ThingDef[defName="Apparel_VestRoyal"]</xpath>
    <value>
      <li Class="LifeLessons.BillProficiencyExtension">
        <requirements>
          <li>Tailoring</li>
        </requirements>
      </li>
    </value>
    <success>Normal</success>
  </Operation>

  <Operation Class="PatchOperationAddModExtension">
    <xpath>Defs/ThingDef[defName="Apparel_RobeRoyal"]</xpath>
    <value>
      <li Class="LifeLessons.BillProficiencyExtension">
        <requirements>
          <li>Tailoring</li>
        </requirements>
      </li>
    </value>
    <success>Normal</success>
  </Operation>

  <Operation Class="PatchOperationAddModExtension">
    <xpath>Defs/ThingDef[defName="Apparel_HatLadies"]</xpath>
    <value>
      <li Class="LifeLessons.BillProficiencyExtension">
        <requirements>
          <li>Tailoring</li>
        </requirements>
      </li>
    </value>
    <success>Normal</success>
  </Operation>

  <Operation Class="PatchOperationAddModExtension">
    <xpath>Defs/ThingDef[defName="Apparel_HatTop"]</xpath>
    <value>
      <li Class="LifeLessons.BillProficiencyExtension">
        <requirements>
          <li>Tailoring</li>
        </requirements>
      </li>
    </value>
    <success>Normal</success>
  </Operation>

  <Operation Class="PatchOperationAddModExtension">
    <xpath>Defs/ThingDef[defName="Apparel_Coronet"]</xpath>
    <value>
      <li Class="LifeLessons.BillProficiencyExtension">
        <requirements>
          <li>Smithing</li>
        </requirements>
      </li>
    </value>
    <success>Normal</success>
  </Operation>

  <Operation Class="PatchOperationAddModExtension">
    <xpath>Defs/ThingDef[defName="Apparel_Crown"]</xpath>
    <value>
      <li Class="LifeLessons.BillProficiencyExtension">
        <requirements>
          <li>Smithing</li>
        </requirements>
      </li>
    </value>
    <success>Normal</success>
  </Operation>

  <Operation Class="PatchOperationAddModExtension">
    <xpath>Defs/ThingDef[defName="Apparel_CrownStellic"]</xpath>
    <value>
      <li Class="LifeLessons.BillProficiencyExtension">
        <requirements>
          <li>Smithing</li>
        </requirements>
      </li>
    </value>
    <success>Normal</success>
  </Operation>

  <Operation Class="PatchOperationAddModExtension">
    <xpath>Defs/ThingDef[defName="Apparel_Cape"]</xpath>
    <value>
      <li Class="LifeLessons.BillProficiencyExtension">
        <requirements>
          <li>Tailoring</li>
        </requirements>
      </li>
    </value>
    <success>Normal</success>
  </Operation>

  <Operation Class="PatchOperationAddModExtension">
    <xpath>Defs/ThingDef[defName="Apparel_Beret"]</xpath>
    <value>
      <li Class="LifeLessons.BillProficiencyExtension">
        <requirements>
          <li>Tailoring</li>
        </requirements>
      </li>
    </value>
    <success>Normal</success>
  </Operation>
</Patch>