<?xml version="1.0" encoding="utf-8"?>
<Patch>
  <Operation Class="PatchOperationAddModExtension">
    <xpath>Defs/ThingDef[defName="RimNauts2_Apparel_SpaceSuit_Head"]</xpath>
    <value>
      <li Class="LifeLessons.BillProficiencyExtension">
        <requirements>
          <li>PowerarmorAssembly</li>
          <li>EnvironmentalChemistry</li>
          <li>MaterialsChemistry</li>
          <li>Glassworking</li>
          <li>Engineering</li>
        </requirements>
        <hardRequirement>True</hardRequirement>
        
        
      </li>
    </value>
  </Operation>
  <Operation Class="PatchOperationAddModExtension">
    <xpath>Defs/ThingDef[defName="RimNauts2_Apparel_SpaceSuit_Body"]</xpath>
    <value>
      <li Class="LifeLessons.BillProficiencyExtension">
        <requirements>
          <li>PowerarmorAssembly</li>
          <li>EnvironmentalChemistry</li>
          <li>MaterialsChemistry</li>
          <li>Glassworking</li>
          <li>Engineering</li>
        </requirements>
        <hardRequirement>True</hardRequirement>
        
        
      </li>
    </value>
  </Operation>
</Patch>