<?xml version="1.0" encoding="utf-8"?>
<Patch>
  <Operation Class="PatchOperationAddModExtension">
    <xpath>Defs/ResearchProjectDef[defName="PRF_BeltsI"]</xpath>
    <value>
      <li Class="LifeLessons.BillProficiencyExtension">
        <requirements>
          <li>Mechanics</li>
          <li>Machining</li>
          <li>Electronics</li>
        </requirements>
        <softRequirement>False</softRequirement>
        <unqualifiedWorkSpeedMultiplier>1</unqualifiedWorkSpeedMultiplier>
        <unqualifiedQualityCap>Legendary</unqualifiedQualityCap>
      </li>
    </value>
  </Operation>
  <Operation Class="PatchOperationAddModExtension">
    <xpath>Defs/ResearchProjectDef[defName="PRF_BeltsII"]</xpath>
    <value>
      <li Class="LifeLessons.BillProficiencyExtension">
        <requirements>
          <li>Mechanics</li>
          <li>Machining</li>
          <li>Electronics</li>
        </requirements>
        <softRequirement>False</softRequirement>
        <unqualifiedWorkSpeedMultiplier>1</unqualifiedWorkSpeedMultiplier>
        <unqualifiedQualityCap>Legendary</unqualifiedQualityCap>
      </li>
    </value>
  </Operation>
  <Operation Class="PatchOperationAddModExtension">
    <xpath>Defs/ResearchProjectDef[defName="PRF_BeltsIII"]</xpath>
    <value>
      <li Class="LifeLessons.BillProficiencyExtension">
        <requirements>
          <li>Engineering</li>
          <li>Machining</li>
        </requirements>
        <softRequirement>False</softRequirement>
        <unqualifiedWorkSpeedMultiplier>1</unqualifiedWorkSpeedMultiplier>
        <unqualifiedQualityCap>Legendary</unqualifiedQualityCap>
      </li>
    </value>
  </Operation>
</Patch>